odoo/addons/l10n_it_fatturapa_out_sp/README.rst
odoo/addons/l10n_it_fatturapa_out_sp/__init__.py
odoo/addons/l10n_it_fatturapa_out_sp/__manifest__.py
odoo/addons/l10n_it_fatturapa_out_sp/i18n/l10n_it_fatturapa_out_sp.pot
odoo/addons/l10n_it_fatturapa_out_sp/readme/CONTRIBUTORS.rst
odoo/addons/l10n_it_fatturapa_out_sp/readme/DESCRIPTION.rst
odoo/addons/l10n_it_fatturapa_out_sp/static/description/icon.png
odoo/addons/l10n_it_fatturapa_out_sp/static/description/index.html
odoo/addons/l10n_it_fatturapa_out_sp/tests/__init__.py
odoo/addons/l10n_it_fatturapa_out_sp/tests/fatturapa_common.py
odoo/addons/l10n_it_fatturapa_out_sp/tests/test_fatturapa_xml_validation.py
odoo/addons/l10n_it_fatturapa_out_sp/tests/data/IT06363391001_00004.xml
odoo/addons/l10n_it_fatturapa_out_sp/wizard/__init__.py
odoo/addons/l10n_it_fatturapa_out_sp/wizard/wizard_export_fatturapa.py
odoo14_addon_l10n_it_fatturapa_out_sp-14.0.1.0.4.dist-info/METADATA
odoo14_addon_l10n_it_fatturapa_out_sp-14.0.1.0.4.dist-info/WHEEL
odoo14_addon_l10n_it_fatturapa_out_sp-14.0.1.0.4.dist-info/top_level.txt
odoo14_addon_l10n_it_fatturapa_out_sp-14.0.1.0.4.dist-info/RECORD
